xml2html/__init__.py
xml2html/cli.py
xml2html/xml2html.py
xml2html-0.2.0.dist-info/DESCRIPTION.rst
xml2html-0.2.0.dist-info/METADATA
xml2html-0.2.0.dist-info/RECORD
xml2html-0.2.0.dist-info/WHEEL
xml2html-0.2.0.dist-info/entry_points.txt
xml2html-0.2.0.dist-info/metadata.json
xml2html-0.2.0.dist-info/top_level.txt
