Metadata-Version: 2.0
Name: xml2html
Version: 0.2.0
Summary: simple html generator for xml files
Home-page: https://github.com/jfunez/xml2html
Author: Juan Funez
Author-email: juan.funez@gmail.com
License: MIT license
Keywords: xml2html
Platform: UNKNOWN
Classifier: Development Status :: 2 - Pre-Alpha
Classifier: Intended Audience :: Developers
Classifier: License :: OSI Approved :: MIT License
Classifier: Natural Language :: English
Classifier: Programming Language :: Python :: 2
Classifier: Programming Language :: Python :: 2.7
Classifier: Programming Language :: Python :: 3
Classifier: Programming Language :: Python :: 3.4
Classifier: Programming Language :: Python :: 3.5
Classifier: Programming Language :: Python :: 3.6
Requires-Dist: Click (>=6.0)
